typegql/__init__.py
typegql/builder/__init__.py
typegql/builder/arguments.py
typegql/builder/base.py
typegql/builder/connection.py
typegql/builder/mutation.py
typegql/builder/query.py
typegql/builder/types.py
typegql/builder/utils.py
typegql/client/__init__.py
typegql/client/client.py
typegql/client/dsl.py
typegql/execution.py
typegql/pubsub.py
typegql/py.typed
typegql/schema.py
typegql-4.0.2.dist-info/WHEEL
typegql-4.0.2.dist-info/METADATA
typegql-4.0.2.dist-info/RECORD
