Metadata-Version: 2.1
Name: typegql
Version: 4.0.2
Summary: A Python GraphQL library that makes use of type hinting and concurrency support with the new async/await syntax.
Home-page: https://github.com/cipriantarta/typegql
License: MIT
Keywords: graphql,python,asyncio,generics,typing
Author: Ciprian Tarta
Author-email: ciprian@cipriantarta.ro
Requires-Python: >=3.7,<4.0
Classifier: Intended Audience :: Developers
Classifier: License :: OSI Approved :: MIT License
Classifier: Programming Language :: Python
Classifier: Programming Language :: Python :: 3
Classifier: Programming Language :: Python :: 3.7
Classifier: Programming Language :: Python :: 3.8
Classifier: Programming Language :: Python :: Implementation :: CPython
Classifier: Programming Language :: Python :: Implementation :: PyPy
Classifier: Topic :: Software Development
Provides-Extra: client
Requires-Dist: aiohttp (>=3.4,<4.0); extra == "client"
Requires-Dist: graphql-core (>=3)
Project-URL: Repository, https://github.com/cipriantarta/typegql
